pypclients/__init__.py
pypclients/bitbucket_client.py
pypclients/files_client.py
pypclients/sql_client.py
pypclients/zipfiles_client.py
pypclients-0.1.0.post3.dist-info/METADATA
pypclients-0.1.0.post3.dist-info/WHEEL
pypclients-0.1.0.post3.dist-info/top_level.txt
pypclients-0.1.0.post3.dist-info/RECORD
