Metadata-Version: 2.4
Name: pypClients
Version: 0.1.0.post3
Summary: Python packages Bitbucket, SQL, Zipfile, misc. files methods
Author-email: Antoine Richado <fordian68@gmail.com>
Classifier: Programming Language :: Python :: 3
Classifier: Operating System :: OS Independent
Requires-Dist: colorama==0.4.6
Requires-Dist: pandas==2.2.3
Requires-Dist: pymssql==2.3.2
Requires-Dist: requests==2.32.3
Requires-Dist: requests-toolbelt==1.0.0
Requires-Dist: types-colorama==0.4.15.20240311
Requires-Dist: types-requests==2.32.0.20241016
Requires-Dist: typing==3.7.4.3
Requires-Dist: typing_extensions==4.12.2
Requires-Dist: urllib3==2.2.3
